simulationworkflownormalizer/__init__.py
simulationworkflownormalizer/nomad_plugin.yaml
simulationworkflownormalizer/normalizer.py
nomad_normalizer_plugin_simulation_workflow-1.0.3.dist-info/LICENSE
nomad_normalizer_plugin_simulation_workflow-1.0.3.dist-info/METADATA
nomad_normalizer_plugin_simulation_workflow-1.0.3.dist-info/WHEEL
nomad_normalizer_plugin_simulation_workflow-1.0.3.dist-info/entry_points.txt
nomad_normalizer_plugin_simulation_workflow-1.0.3.dist-info/top_level.txt
nomad_normalizer_plugin_simulation_workflow-1.0.3.dist-info/RECORD
